{
  "Airgetlam": {
    "affinity": "eooaoooow",
    "atks": [
      6,
      75,
      57
    ],
    "disinherits": [
      "wind"
    ],
    "drops": "Claimh Solais",
    "growth": "Melee Skill",
    "lvl": 12,
    "mresists": "ss-Rwwww----TS",
    "presists": "-----------w--",
    "race": "Emperor",
    "skills": [
      "Magna",
      "Paralama",
      "Dormina",
      "-",
      "Mamagnara",
      "Ichimonji Slash"
    ],
    "stats": [
      18,
      9,
      7,
      16,
      12
    ],
    "subtype": "Earth",
    "type": "Element"
  },
  "Aizen Myouou": {
    "affinity": "wwwewwwww",
    "atks": [
      4,
      39,
      69
    ],
    "disinherits": [
      "curse"
    ],
    "drops": "Vi Incense",
    "growth": "Early Growth",
    "lvl": 6,
    "mresists": "ssssssssdVxdTS",
    "presists": "xxxxxxxx-w--xx",
    "race": "Hierophant",
    "skills": [
      "Hama",
      "Candy Voice",
      "Sukukaja",
      "Fist of Fury",
      "Makakaja",
      "Eternal White"
    ],
    "stats": [
      10,
      12,
      9,
      5,
      7
    ],
    "subtype": "Occult",
    "type": "Light"
  },
  "Amatsu Mikaboshi": {
    "affinity": "oaoooaaae",
    "atks": [
      70,
      246,
      201
    ],
    "disinherits": [
      "expel",
      "bless",
      "miracle"
    ],
    "drops": "Doggerel Tablet",
    "growth": "Defense Skill",
    "lvl": 88,
    "mresists": "--------xwdsnS",
    "presists": "SSSSSxSSnnnn--",
    "race": "Tower",
    "skills": [
      "Dormina",
      "Mamudo",
      "Delyte",
      "Makajam",
      "Decover",
      "Lightning Kick"
    ],
    "stats": [
      83,
      78,
      43,
      39,
      68
    ],
    "subtype": "Nerve",
    "type": "Dark"
  },
  "Ame no Uzume": {
    "affinity": "oeoooooaw",
    "atks": [
      5,
      75,
      75
    ],
    "disinherits": [
      "death",
      "curse"
    ],
    "drops": "Petradi Stone",
    "growth": "Support Skill",
    "lvl": 11,
    "mresists": "ssssTTTTddxxRS",
    "presists": "---x--xx-----w",
    "race": "Priestess",
    "skills": [
      "Media",
      "Happy Dance",
      "Agi",
      "Paraladi",
      "Diarama",
      "Sexy Dance"
    ],
    "stats": [
      11,
      13,
      14,
      6,
      7
    ],
    "subtype": "Bless",
    "type": "Light"
  },
  "Amen Ra": {
    "affinity": "ewwwwwwww",
    "atks": [
      20,
      187,
      162
    ],
    "disinherits": [],
    "drops": "Evil Fire Tablet",
    "growth": "Tech Skill",
    "lvl": 62,
    "mresists": "ssssxdWW----TS",
    "presists": "-----------w--",
    "race": "Emperor",
    "skills": [
      "Agilao",
      "Agidyne",
      "Shibaboo",
      "Shuuraigeki",
      "Azure Cessation",
      "Hieroglyphein"
    ],
    "stats": [
      68,
      31,
      26,
      53,
      36
    ],
    "subtype": "Nuclear",
    "type": "Element"
  },
  "Ankou": {
    "affinity": "aoaaaaaoe",
    "atks": [
      18,
      139,
      119
    ],
    "disinherits": [
      "expel",
      "bless",
      "miracle"
    ],
    "drops": "Yuuma Ankoku Sho",
    "growth": "Early Growth",
    "lvl": 44,
    "mresists": "nnnn----xxdnrS",
    "presists": "---x--------nn",
    "race": "Death",
    "skills": [
      "Baeiha",
      "Decover",
      "Doroid",
      "-",
      "Deathtika",
      "Earth Slicer"
    ],
    "stats": [
      23,
      18,
      44,
      39,
      49
    ],
    "subtype": "Death",
    "type": "Dark"
  },
  "Anubis": {
    "affinity": "oeoooeeeo",
    "atks": [
      11,
      99,
      109
    ],
    "disinherits": [],
    "drops": "Prosecutor's Diary",
    "growth": "Defense Skill",
    "lvl": 32,
    "mresists": "--------dsxxrs",
    "presists": "----x---VWVVnn",
    "race": "Temperance",
    "skills": [
      "Drumroll Punch",
      "Alsanga",
      "-",
      "Dark Verdict",
      "-",
      "Recarmdra"
    ],
    "stats": [
      36,
      23,
      51,
      26,
      17
    ],
    "subtype": "Prayer",
    "type": "Force"
  },
  "Aonbharr": {
    "affinity": "oeoooeeeo",
    "atks": [
      13,
      97,
      84
    ],
    "disinherits": [
      "ice"
    ],
    "drops": "Dordona's Oar",
    "growth": "Early Growth",
    "lvl": 25,
    "mresists": "--------dsxxrs",
    "presists": "----x---VWVVnn",
    "race": "Hermit",
    "skills": [
      "Maragi",
      "Alsanga",
      "Magnara",
      "Traesto",
      "Eastern Impact",
      "Virus Claw"
    ],
    "stats": [
      20,
      29,
      44,
      23,
      13
    ],
    "subtype": "Fire",
    "type": "Element"
  },
  "Arianrhod": {
    "affinity": "oaoooooew",
    "atks": [
      17,
      98,
      98
    ],
    "disinherits": [],
    "drops": "Eleking Glove",
    "growth": "Attack Skill",
    "lvl": 27,
    "mresists": "wwwwssR-----TS",
    "presists": "-----------w--",
    "race": "Empress",
    "skills": [
      "Mazan",
      "-",
      "Zionga",
      "Twin Slash",
      "-",
      "Zanma"
    ],
    "stats": [
      26,
      25,
      21,
      11,
      26
    ],
    "subtype": "Blast",
    "type": "Force"
  },
  "Armaiti": {
    "affinity": "oooooeaow",
    "atks": [
      30,
      172,
      162
    ],
    "disinherits": [
      "death",
      "curse"
    ],
    "drops": "Angel Whisper",
    "growth": "Defense Skill",
    "lvl": 55,
    "mresists": "RRRRRRRRRRxxRs",
    "presists": "--x----x-w---x",
    "race": "Judgement",
    "skills": [
      "Gokuraku Fall",
      "Mediarahan",
      "-",
      "Dekunda",
      "Makouha",
      "Petra Eyes"
    ],
    "stats": [
      32,
      27,
      22,
      58,
      36
    ],
    "subtype": "Bless",
    "type": "Light"
  },
  "Azrael": {
    "affinity": "oooooeaow",
    "atks": [
      19,
      133,
      128
    ],
    "disinherits": [
      "curse"
    ],
    "drops": "Ziodyne Stone",
    "growth": "Melee Skill",
    "lvl": 36,
    "mresists": "nnnnnnnndnxxns",
    "presists": "wwxwwwwx-w---x",
    "race": "Judgement",
    "skills": [
      "Wing Flap",
      "Baikouha",
      "Frenzy Song",
      "Recarmdra",
      "Tarukaja",
      "Dark Verdict"
    ],
    "stats": [
      24,
      19,
      14,
      43,
      27
    ],
    "subtype": "Miracle",
    "type": "Light"
  },
  "Baal": {
    "affinity": "eooaoooow",
    "atks": [
      26,
      167,
      147
    ],
    "disinherits": [],
    "drops": "Caesar Guard",
    "growth": "Attack Skill",
    "lvl": 55,
    "mresists": "ss-Rwwww----TS",
    "presists": "-----------w--",
    "race": "Emperor",
    "skills": [
      "Bufula",
      "Makajam",
      "Gentle Wave",
      "-",
      "Bufudyne",
      "Bright Judgement"
    ],
    "stats": [
      63,
      27,
      22,
      48,
      32
    ],
    "subtype": "Earth",
    "type": "Element"
  },
  "Barbatos": {
    "affinity": "oooaeoeae",
    "atks": [
      24,
      178,
      155
    ],
    "disinherits": [
      "expel",
      "bless",
      "miracle"
    ],
    "drops": "Reaper Colt",
    "growth": "Late Growth A",
    "lvl": 59,
    "mresists": "RRRRRRRRxxRRrs",
    "presists": "--x----xw----x",
    "race": "Hanged",
    "skills": [
      "Paral Eyes",
      "Luna Trap",
      "Twinkle Punch",
      "Pulinpa",
      "Doronpa",
      "Maeiha"
    ],
    "stats": [
      24,
      29,
      34,
      60,
      55
    ],
    "subtype": "Occult",
    "type": "Dark"
  },
  "Beelzebub": {
    "affinity": "wwwwwwwwe",
    "atks": [
      66,
      233,
      208
    ],
    "disinherits": [
      "expel",
      "bless",
      "miracle"
    ],
    "drops": "Dark Wave Tablet",
    "growth": "Balanced A",
    "lvl": 77,
    "mresists": "SSSSSSSSxxdRnS",
    "presists": "ssxsssssssssss",
    "race": "Devil",
    "skills": [
      "Genocide Fan",
      "Mamudo",
      "Crystal Wall",
      "Nervma",
      "Deathtika",
      "Moon Shatterer"
    ],
    "stats": [
      31,
      51,
      36,
      41,
      64
    ],
    "subtype": "Curse",
    "type": "Dark"
  },
  "Bennu": {
    "affinity": "oeoooeeeo",
    "atks": [
      6,
      57,
      52
    ],
    "disinherits": [
      "ice"
    ],
    "drops": "Posumudi Stone",
    "growth": "Support Skill",
    "lvl": 10,
    "mresists": "ssn-wwTx-s-sTs",
    "presists": "nn-nn-xnXXXX--",
    "race": "Sun",
    "skills": [
      "Beak",
      "Maragi",
      "-",
      "Magaru",
      "Agilao",
      "Fire Breath"
    ],
    "stats": [
      14,
      7,
      9,
      31,
      16
    ],
    "subtype": "Fire",
    "type": "Element"
  },
  "Bishamonten": {
    "affinity": "ooaoeooow",
    "atks": [
      33,
      195,
      155
    ],
    "disinherits": [
      "bless",
      "miracle"
    ],
    "drops": "Evil Ice Tablet",
    "growth": "Late Growth B",
    "lvl": 66,
    "mresists": "wwwwss-R----TS",
    "presists": "-----------w--",
    "race": "Justice",
    "skills": [
      "Grydyne",
      "-",
      "Magrydyne",
      "Triple Slice",
      "-",
      "Ziodyne"
    ],
    "stats": [
      31,
      36,
      65,
      60,
      45
    ],
    "subtype": "Gravity",
    "type": "Force"
  },
  "Brahma": {
    "affinity": "eooaoooow",
    "atks": [
      10,
      95,
      80
    ],
    "disinherits": [],
    "drops": "Agidyne Stone",
    "growth": "Magic Skill",
    "lvl": 23,
    "mresists": "xxxxXXXX-x-x--",
    "presists": "dddddddddddddd",
    "race": "Emperor",
    "skills": [
      "Bufula",
      "Liftoma",
      "-",
      "Mabufula",
      "Deathtika",
      "Rainbow Strike"
    ],
    "stats": [
      27,
      13,
      10,
      22,
      18
    ],
    "subtype": "Expel",
    "type": "Element"
  },
  "Bres": {
    "affinity": "wwwwwwwwe",
    "atks": [
      9,
      114,
      99
    ],
    "disinherits": [
      "expel",
      "bless",
      "miracle"
    ],
    "drops": "Megidola Stone",
    "growth": "Early Growth",
    "lvl": 10,
    "mresists": "SSSSSSSSxxdRnS",
    "presists": "ssxsssssssssss",
    "race": "Devil",
    "skills": [
      "Twin Slash",
      "Balzac",
      "Eiha",
      "Quikka",
      "Makajam",
      "Eastern Impact"
    ],
    "stats": [
      15,
      20,
      13,
      18,
      24
    ],
    "subtype": "Occult",
    "type": "Dark"
  },
  "Brigid": {
    "affinity": "oaoooooew",
    "atks": [
      19,
      117,
      117
    ],
    "disinherits": [],
    "drops": "Raydog",
    "growth": "Vanguard Skill",
    "lvl": 36,
    "mresists": "wwwwR-ss----TS",
    "presists": "-----------w--",
    "race": "Empress",
    "skills": [
      "Frei",
      "Diarama",
      "Freila",
      "Freidyne",
      "-",
      "Azure Cessation"
    ],
    "stats": [
      30,
      29,
      25,
      14,
      33
    ],
    "subtype": "Electric",
    "type": "Force"
  },
  "Byakko": {
    "affinity": "eeeeeeeee",
    "atks": [
      18,
      126,
      113
    ],
    "disinherits": [
      "earth"
    ],
    "drops": "Byakko Greaves",
    "growth": "Byakko",
    "lvl": 39,
    "mresists": "--------dsxxrs",
    "presists": "----x---VWVVnn",
    "race": "Hermit",
    "skills": [
      "Poison Claw",
      "Garula",
      "Estoma",
      "Bind Voice",
      "Magarula",
      "Stone Bite"
    ],
    "stats": [
      28,
      40,
      55,
      30,
      21
    ],
    "subtype": "Wind",
    "type": "Element"
  },
  "Cerberus": {
    "affinity": "eeeeeeeee",
    "atks": [
      15,
      123,
      125
    ],
    "disinherits": [],
    "drops": "Dead Ends",
    "growth": "Late Growth B",
    "lvl": 40,
    "mresists": "--------dsxxrs",
    "presists": "----x---VWVVnn",
    "race": "Fortune",
    "skills": [
      "Venom Bite",
      "Wolvaan",
      "Tetraja",
      "Tackle",
      "Recarm",
      "Virus Claw"
    ],
    "stats": [
      31,
      29,
      55,
      30,
      21
    ],
    "subtype": "Death",
    "type": "Light"
  },
  "Cu Chulainn": {
    "affinity": "oooooaeow",
    "atks": [
      18,
      115,
      80
    ],
    "disinherits": [
      "wind"
    ],
    "drops": "Gae Bolg",
    "growth": "Attack Skill",
    "lvl": 28,
    "mresists": "ss-Rwwww----TS",
    "presists": "-----------w--",
    "race": "Magician",
    "skills": [
      "Double Thrust",
      "Magnara",
      "Mamagna",
      "Estoma",
      "Outoma",
      "Dragon Whirl"
    ],
    "stats": [
      21,
      15,
      27,
      32,
      12
    ],
    "subtype": "Earth",
    "type": "Element"
  },
  "Durga": {
    "affinity": "wwwwwwwew",
    "atks": [
      20,
      166,
      131
    ],
    "disinherits": [],
    "drops": "Infinity",
    "growth": "Attack Skill",
    "lvl": 57,
    "mresists": "wwwwR-ss----TS",
    "presists": "-----------w--",
    "race": "Empress",
    "skills": [
      "Gryva",
      "Eternal Black",
      "Wolf Fang",
      "-",
      "Gokuraku Fall",
      "Maziodyne"
    ],
    "stats": [
      41,
      40,
      36,
      23,
      49
    ],
    "subtype": "Electric",
    "type": "Force"
  },
  "Freyr": {
    "affinity": "wwwwwweww",
    "atks": [
      20,
      190,
      150
    ],
    "disinherits": [
      "wind"
    ],
    "drops": "Caesar Leg",
    "growth": "Late Growth B",
    "lvl": 59,
    "mresists": "ss-Rwwww----TS",
    "presists": "-----------w--",
    "race": "Magician",
    "skills": [
      "Magnara",
      "Mamagnara",
      "Mamagnadyne",
      "Rainbow Strike",
      "Gentle Wave",
      "Destruction Smash"
    ],
    "stats": [
      40,
      29,
      50,
      55,
      24
    ],
    "subtype": "Earth",
    "type": "Element"
  },
  "Fuhedi Mergane": {
    "affinity": "aooeoooow",
    "atks": [
      41,
      192,
      202
    ],
    "disinherits": [
      "curse"
    ],
    "drops": "Flash Tablet",
    "growth": "Late Growth A",
    "lvl": 74,
    "mresists": "ssDsdVssdnxWTn",
    "presists": "---------w----",
    "race": "Hierophant",
    "skills": [
      "Shuuraigeki",
      "-",
      "Rakunda",
      "-",
      "Arrow Volley",
      "Makarakarn"
    ],
    "stats": [
      40,
      71,
      61,
      35,
      49
    ],
    "subtype": "Electric",
    "type": "Light"
  },
  "Fuutai": {
    "affinity": "oeoooeeeo",
    "atks": [
      7,
      72,
      65
    ],
    "disinherits": [
      "fire"
    ],
    "drops": "Bufudyne Stone",
    "growth": "Rear Guard Skill",
    "lvl": 16,
    "mresists": "--------dsxxrs",
    "presists": "----x---VWVVnn",
    "race": "Hermit",
    "skills": [
      "Bufula",
      "Garu",
      "Panic Voice",
      "Stone Claw",
      "-",
      "Mighty Wave"
    ],
    "stats": [
      15,
      22,
      27,
      18,
      9
    ],
    "subtype": "Ice",
    "type": "Element"
  },
  "Garuda": {
    "affinity": "oeoooeeeo",
    "atks": [
      58,
      217,
      197
    ],
    "disinherits": [
      "earth"
    ],
    "drops": "Evil Wind Tablet",
    "growth": "Balanced B",
    "lvl": 79,
    "mresists": "ssn-wwTx-s-sTs",
    "presists": "nn-nn-xnXXXX--",
    "race": "Sun",
    "skills": [
      "Magarula",
      "Spike Claw",
      "Earthly Vortex",
      "Garudyne",
      "Death Claw",
      "Magarudyne"
    ],
    "stats": [
      49,
      37,
      52,
      86,
      71
    ],
    "subtype": "Wind",
    "type": "Element"
  },
  "Genbu": {
    "affinity": "eeeeeeeee",
    "atks": [
      25,
      141,
      129
    ],
    "disinherits": [
      "fire"
    ],
    "drops": "Genbu Armor",
    "growth": "Genbu",
    "lvl": 45,
    "mresists": "--------dsxxrs",
    "presists": "----x---VWVVnn",
    "race": "Temperance",
    "skills": [
      "Ice Breath",
      "Magnara",
      "-",
      "Gentle Wave",
      "Makakaja",
      "Mamagnara"
    ],
    "stats": [
      45,
      32,
      60,
      33,
      23
    ],
    "subtype": "Ice",
    "type": "Force"
  },
  "Gozu-Tennoh": {
    "affinity": "ooeoaooow",
    "atks": [
      8,
      79,
      54
    ],
    "disinherits": [
      "bless",
      "miracle"
    ],
    "drops": "Grydyne Stone",
    "growth": "Attack Skill",
    "lvl": 18,
    "mresists": "wwww-rss----TS",
    "presists": "-----------w--",
    "race": "Chariot",
    "skills": [
      "Squash",
      "Toxic Sting",
      "-",
      "Megido",
      "Thunder Kick",
      "Megidola"
    ],
    "stats": [
      21,
      18,
      20,
      11,
      16
    ],
    "subtype": "Nuclear",
    "type": "Force"
  },
  "Hanuman": {
    "affinity": "oooooaeow",
    "atks": [
      51,
      216,
      169
    ],
    "disinherits": [
      "earth"
    ],
    "drops": "Evil Quake Tablet",
    "growth": "Balanced A",
    "lvl": 68,
    "mresists": "ssR-wwww----TS",
    "presists": "-----------w--",
    "race": "Magician",
    "skills": [
      "Garula",
      "Lightning Kick",
      "Magarula",
      "Magarudyne",
      "Heavenly Cyclone",
      "Triple Slice"
    ],
    "stats": [
      45,
      33,
      57,
      63,
      28
    ],
    "subtype": "Wind",
    "type": "Element"
  },
  "Hathor": {
    "affinity": "oeoooooaw",
    "atks": [
      10,
      112,
      112
    ],
    "disinherits": [
      "curse"
    ],
    "drops": "Freidyne Stone",
    "growth": "Magic Skill",
    "lvl": 29,
    "mresists": "ssssTTTTddxxRS",
    "presists": "---x--xx-----w",
    "race": "Priestess",
    "skills": [
      "Patra",
      "Nervundi",
      "Love Whip",
      "Alsanga",
      "Mediarama",
      "Hell Eyes"
    ],
    "stats": [
      20,
      22,
      28,
      10,
      15
    ],
    "subtype": "Expel",
    "type": "Light"
  },
  "Hel": {
    "affinity": "aoaaaoooe",
    "atks": [
      16,
      113,
      98
    ],
    "disinherits": [
      "expel",
      "bless",
      "miracle"
    ],
    "drops": "Petra Stone",
    "growth": "Late Growth B",
    "lvl": 34,
    "mresists": "nnnn----xxdnrS",
    "presists": "---x--------nn",
    "race": "Death",
    "skills": [
      "Eiha",
      "Marin Karin",
      "Liftoma",
      "Slumpa",
      "-",
      "Hell Eyes"
    ],
    "stats": [
      19,
      15,
      36,
      31,
      41
    ],
    "subtype": "Curse",
    "type": "Dark"
  },
  "Hermod": {
    "affinity": "oooooaeow",
    "atks": [
      23,
      135,
      100
    ],
    "disinherits": [],
    "drops": "Vidar's Shoes",
    "growth": "Magic Skill",
    "lvl": 35,
    "mresists": "ssssssss-x-dsS",
    "presists": "xxxxxxxx---w--",
    "race": "Magician",
    "skills": [
      "Magaru",
      "Garula",
      "Magarula",
      "-",
      "Tackle",
      "Infinite Spiral"
    ],
    "stats": [
      26,
      19,
      32,
      38,
      15
    ],
    "subtype": "Curse",
    "type": "Element"
  },
  "Hokuto Seikun": {
    "affinity": "ooeoaooow",
    "atks": [
      12,
      116,
      86
    ],
    "disinherits": [
      "bless",
      "miracle"
    ],
    "drops": "Wu Huo Shen Yan Shan",
    "growth": "Attack Skill",
    "lvl": 33,
    "mresists": "wwwwR-ss----TS",
    "presists": "-----------w--",
    "race": "Chariot",
    "skills": [
      "Fist of Fury",
      "-",
      "Zionga",
      "-",
      "Magryva",
      "Viper Smash"
    ],
    "stats": [
      41,
      28,
      36,
      18,
      23
    ],
    "subtype": "Electric",
    "type": "Force"
  },
  "Houri": {
    "affinity": "wwwwwweww",
    "atks": [
      8,
      60,
      48
    ],
    "disinherits": [
      "ice"
    ],
    "drops": "Balm of Life",
    "growth": "Early Growth",
    "lvl": 8,
    "mresists": "R-sswwww----TS",
    "presists": "-----------w--",
    "race": "Magician",
    "skills": [
      "Agilao",
      "Lullaby",
      "-",
      "Maragi",
      "Love Whip",
      "Crimson Sublation"
    ],
    "stats": [
      7,
      7,
      11,
      12,
      6
    ],
    "subtype": "Fire",
    "type": "Element"
  },
  "Ildanach": {
    "affinity": "oooooaeow",
    "atks": [
      61,
      249,
      194
    ],
    "disinherits": [],
    "drops": "Brionac",
    "growth": "Balanced B",
    "lvl": 80,
    "mresists": "ssssxdWW----TS",
    "presists": "-----------w--",
    "race": "Magician",
    "skills": [
      "Agidyne",
      "Deathbound",
      "Maragion",
      "Maragidyne",
      "Bright Judgement",
      "Burning Spear"
    ],
    "stats": [
      53,
      37,
      67,
      72,
      32
    ],
    "subtype": "Nuclear",
    "type": "Element"
  },
  "Illuyanka": {
    "affinity": "eoeeeoooe",
    "atks": [
      11,
      102,
      105
    ],
    "disinherits": [],
    "drops": "Kris Naga",
    "growth": "Attack Skill",
    "lvl": 29,
    "mresists": "wwwwwwwwdsxxss",
    "presists": "ssssssssssssxs",
    "race": "World",
    "skills": [
      "Poison Breath",
      "Gryva",
      "Virus Bite",
      "-",
      "Bonecrusher",
      "Megidola"
    ],
    "stats": [
      28,
      48,
      17,
      15,
      20
    ],
    "subtype": "Wind",
    "type": "Force"
  },
  "Indra": {
    "affinity": "aooeoooow",
    "atks": [
      62,
      233,
      233
    ],
    "disinherits": [
      "curse"
    ],
    "drops": "Holy Writ Tablet",
    "growth": "Balanced B",
    "lvl": 89,
    "mresists": "ssDsdVssdnxWTn",
    "presists": "---------w----",
    "race": "Hierophant",
    "skills": [
      "Mahama",
      "-",
      "Burning Spear",
      "Sanraigeki",
      "Dekaja",
      "Maziodyne"
    ],
    "stats": [
      45,
      83,
      73,
      40,
      58
    ],
    "subtype": "Electric",
    "type": "Light"
  },
  "Ishtar": {
    "affinity": "oaoooooew",
    "atks": [
      44,
      188,
      178
    ],
    "disinherits": [],
    "drops": "Morning Star",
    "growth": "Late Growth B",
    "lvl": 65,
    "mresists": "wwww-rss----TS",
    "presists": "-----------w--",
    "race": "Empress",
    "skills": [
      "Mazionga",
      "-",
      "Arrow Volley",
      "Recarm",
      "Ziodyne",
      "Freidyne"
    ],
    "stats": [
      45,
      44,
      40,
      26,
      55
    ],
    "subtype": "Nuclear",
    "type": "Force"
  },
  "Jack Frost": {
    "affinity": "oeoooeeew",
    "atks": [
      7,
      57,
      82
    ],
    "disinherits": [
      "fire"
    ],
    "drops": "Lu Incense",
    "growth": "Early Growth",
    "lvl": 10,
    "mresists": "-Rsswwww----TS",
    "presists": "-----------w--",
    "race": "Lovers",
    "skills": [
      "Bufu",
      "Hapirma",
      "Tango of Dispelling",
      "Mabufu",
      "Sweet Trap",
      "Ice Breath"
    ],
    "stats": [
      7,
      12,
      9,
      14,
      26
    ],
    "subtype": "Ice",
    "type": "Element"
  },
  "Janus": {
    "affinity": "wewwweeew",
    "atks": [
      24,
      88,
      102
    ],
    "disinherits": [],
    "drops": "Mandau Spoon",
    "growth": "Rear Guard Skill",
    "lvl": 22,
    "mresists": "--xdn-x------s",
    "presists": "---x------w-w-",
    "race": "Star",
    "skills": [
      "Magna",
      "Spin Kick",
      "Eternal White",
      "Eternal Black",
      "Magarula",
      "Maragion"
    ],
    "stats": [
      20,
      19,
      20,
      26,
      18
    ],
    "subtype": "Earth",
    "type": "Element"
  },
  "Kali": {
    "affinity": "oaoooooew",
    "atks": [
      55,
      240,
      220
    ],
    "disinherits": [],
    "drops": "Wall Tablet",
    "growth": "Balanced A",
    "lvl": 85,
    "mresists": "wwwwss-R----TS",
    "presists": "-----------w--",
    "race": "Empress",
    "skills": [
      "Grydyne",
      "-",
      "Triple Slice",
      "Diarahan",
      "Magrydyne",
      "Eternal Black"
    ],
    "stats": [
      44,
      85,
      39,
      34,
      70
    ],
    "subtype": "Gravity",
    "type": "Force"
  },
  "Kamakura Gongorou": {
    "affinity": "eeeeeeeee",
    "atks": [
      22,
      191,
      161
    ],
    "disinherits": [],
    "drops": "Ameno-Nuboko",
    "growth": "Balanced A",
    "lvl": 61,
    "mresists": "SSSSSSSSSSSSSS",
    "presists": "SSSSSSSSSSSSSS",
    "race": "Fool",
    "skills": [
      "Drumroll Punch",
      "Maragidyne",
      "Sonic Bullet",
      "Maeiha",
      "Makouha",
      "Megidolaon"
    ],
    "stats": [
      51,
      49,
      47,
      48,
      48
    ],
    "subtype": "Normal",
    "type": "Force"
  },
  "Lakshmi": {
    "affinity": "oeoooooaw",
    "atks": [
      35,
      208,
      198
    ],
    "disinherits": [
      "death",
      "curse"
    ],
    "drops": "Half Moon Tablet",
    "growth": "Balanced B",
    "lvl": 70,
    "mresists": "ssssTTTTddxxRS",
    "presists": "---x--xx-----w",
    "race": "Priestess",
    "skills": [
      "Happy Dance",
      "Nervundi",
      "Water Wall",
      "Samarecarm",
      "Fire Wall",
      "Recarmdra"
    ],
    "stats": [
      38,
      47,
      59,
      28,
      33
    ],
    "subtype": "Bless",
    "type": "Light"
  },
  "Lilim": {
    "affinity": "eweeewwwe",
    "atks": [
      21,
      105,
      104
    ],
    "disinherits": [
      "expel",
      "bless",
      "miracle"
    ],
    "drops": "Nerve Stone",
    "growth": "Early Growth",
    "lvl": 21,
    "mresists": "ddddddddxxddrs",
    "presists": "xxxxxxxx----xx",
    "race": "Moon",
    "skills": [
      "Poisma",
      "Slumpa",
      "Toxic Sting",
      "Mudo",
      "Candy Voice",
      "Nervma"
    ],
    "stats": [
      13,
      18,
      18,
      17,
      23
    ],
    "subtype": "Nerve",
    "type": "Dark"
  },
  "Loki": {
    "affinity": "ooooooooe",
    "atks": [
      31,
      174,
      154
    ],
    "disinherits": [
      "expel",
      "bless",
      "miracle"
    ],
    "drops": "Shinsa Bakunetsu Sho",
    "growth": "Vanguard Skill",
    "lvl": 51,
    "mresists": "SSSSSSSSxxdRnS",
    "presists": "ssxsssssssssss",
    "race": "Devil",
    "skills": [
      "Baeiha",
      "Wolvaan",
      "Marin Karin",
      "Bind Voice",
      "Mador",
      "Fist of Fury"
    ],
    "stats": [
      20,
      33,
      25,
      30,
      44
    ],
    "subtype": "Nerve",
    "type": "Dark"
  },
  "Lucifer": {
    "affinity": "aaaaaaaae",
    "atks": [
      100,
      279,
      264
    ],
    "disinherits": [
      "expel",
      "bless",
      "miracle"
    ],
    "drops": "Falsehood Tablet",
    "growth": "Lucifer",
    "lvl": 99,
    "mresists": "SSSSSSSSxxdRnS",
    "presists": "ssxsssssssssss",
    "race": "Devil",
    "skills": [
      "Maeiha",
      "Hell Drop",
      "Mamudo",
      "-",
      "Hell Eyes",
      "Dark Verdict"
    ],
    "stats": [
      40,
      64,
      45,
      50,
      82
    ],
    "subtype": "Miracle",
    "type": "Dark"
  },
  "Macha": {
    "affinity": "ooaoeooow",
    "atks": [
      14,
      105,
      75
    ],
    "disinherits": [
      "earth",
      "bless",
      "miracle"
    ],
    "drops": "Garudyne Stone",
    "growth": "Support Skill",
    "lvl": 28,
    "mresists": "WWdxssss----TS",
    "presists": "-----------w--",
    "race": "Justice",
    "skills": [
      "Zanma",
      "Toxic Sting",
      "Earthly Vortex",
      "-",
      "Mazanma",
      "Zandyne"
    ],
    "stats": [
      15,
      20,
      37,
      32,
      21
    ],
    "subtype": "Wind",
    "type": "Force"
  },
  "Marduk": {
    "affinity": "eooaoooow",
    "atks": [
      23,
      118,
      103
    ],
    "disinherits": [],
    "drops": "Raime Gauntlet",
    "growth": "Vanguard Skill",
    "lvl": 34,
    "mresists": "ssssWWdx----TS",
    "presists": "-----------w--",
    "race": "Emperor",
    "skills": [
      "Agilao",
      "Balzac",
      "-",
      "Maragion",
      "Heat Wave",
      "Tetrakarn"
    ],
    "stats": [
      40,
      19,
      14,
      31,
      24
    ],
    "subtype": "Blast",
    "type": "Element"
  },
  "Maso": {
    "affinity": "wewwwwwww",
    "atks": [
      4,
      67,
      68
    ],
    "disinherits": [
      "fire",
      "death",
      "curse"
    ],
    "drops": "SP Incense",
    "growth": "Early Growth",
    "lvl": 5,
    "mresists": "VdssssssdnxWTn",
    "presists": "---------w----",
    "race": "Priestess",
    "skills": [
      "Bufu",
      "Dia",
      "Posumudi",
      "Rapid Fire",
      "Liftoma",
      "Gentle Wave"
    ],
    "stats": [
      8,
      10,
      12,
      9,
      11
    ],
    "subtype": "Ice",
    "type": "Light"
  },
  "Michael": {
    "affinity": "wwwwwewww",
    "atks": [
      20,
      206,
      181
    ],
    "disinherits": [
      "death",
      "curse"
    ],
    "drops": "Heaven's Gate",
    "growth": "Late Growth B",
    "lvl": 62,
    "mresists": "RRRRRRRRRRxxRs",
    "presists": "--x----x-w---x",
    "race": "Judgement",
    "skills": [
      "Deathbound",
      "Tarukaja",
      "Makouha",
      "Paral Eyes",
      "Dekaja",
      "Tetrakarn"
    ],
    "stats": [
      51,
      31,
      33,
      65,
      43
    ],
    "subtype": "Expel",
    "type": "Light"
  },
  "Mokosh": {
    "affinity": "oaoooooew",
    "atks": [
      6,
      78,
      73
    ],
    "disinherits": [],
    "drops": "Paraladi Stone",
    "growth": "Late Growth A",
    "lvl": 15,
    "mresists": "WWxdssss----TS",
    "presists": "-----------w--",
    "race": "Empress",
    "skills": [
      "Gry",
      "Zio",
      "Zan",
      "-",
      "Hell Drop",
      "Fastball"
    ],
    "stats": [
      17,
      16,
      15,
      9,
      16
    ],
    "subtype": "Earth",
    "type": "Force"
  },
  "Morrigan": {
    "affinity": "ooaoeooow",
    "atks": [
      21,
      147,
      113
    ],
    "disinherits": [
      "earth",
      "bless",
      "miracle"
    ],
    "drops": "Hisou Futakage",
    "growth": "Balanced C",
    "lvl": 46,
    "mresists": "WWdxssss----TS",
    "presists": "-----------w--",
    "race": "Justice",
    "skills": [
      "Wing Flap",
      "-",
      "Zandyne",
      "-",
      "Mazandyne",
      "Burning Spear"
    ],
    "stats": [
      23,
      28,
      51,
      46,
      33
    ],
    "subtype": "Wind",
    "type": "Force"
  },
  "Mot": {
    "affinity": "wwwwwwwwe",
    "atks": [
      20,
      168,
      148
    ],
    "disinherits": [
      "expel",
      "bless",
      "miracle"
    ],
    "drops": "Death Cross",
    "growth": "Support Skill",
    "lvl": 58,
    "mresists": "nnnn----xxdnrS",
    "presists": "---x--------nn",
    "race": "Death",
    "skills": [
      "Maeiha",
      "Wolvaan",
      "-",
      "Makajam",
      "Petra Eyes",
      "Deadly Fist"
    ],
    "stats": [
      29,
      24,
      55,
      50,
      60
    ],
    "subtype": "Death",
    "type": "Dark"
  },
  "Mucalinda": {
    "affinity": "eoeeeoooe",
    "atks": [
      57,
      211,
      204
    ],
    "disinherits": [],
    "drops": "Senko Rinda",
    "growth": "Late Growth B",
    "lvl": 76,
    "mresists": "wwwwwwwwdsxxss",
    "presists": "ssssssssssssxs",
    "race": "World",
    "skills": [
      "Zionga",
      "Freidyne",
      "-",
      "Crystal Wall",
      "Bright Judgement",
      "Magrydyne"
    ],
    "stats": [
      51,
      83,
      40,
      35,
      43
    ],
    "subtype": "Prayer",
    "type": "Force"
  },
  "Narukami": {
    "affinity": "eeeeeeeee",
    "atks": [
      16,
      156,
      131
    ],
    "disinherits": [],
    "drops": "Hell Rain",
    "growth": "Balanced B",
    "lvl": 47,
    "mresists": "SSSSSSSSSSSSSS",
    "presists": "SSSSSSSSSSSSSS",
    "race": "Fool",
    "skills": [
      "Gentle Wave",
      "Mabufudyne",
      "Mahama",
      "Mamudo",
      "Maziodyne",
      "Viper Smash"
    ],
    "stats": [
      43,
      40,
      39,
      38,
      45
    ],
    "subtype": "Normal",
    "type": "Force"
  },
  "Nemhain": {
    "affinity": "wwwwewwww",
    "atks": [
      7,
      53,
      43
    ],
    "disinherits": [
      "earth",
      "bless",
      "miracle"
    ],
    "drops": "Ag Incense",
    "growth": "Early Growth",
    "lvl": 8,
    "mresists": "WWdxssss----TS",
    "presists": "-----------w--",
    "race": "Justice",
    "skills": [
      "Zan",
      "Stun Needle",
      "-",
      "Mazan",
      "-",
      "Heavenly Cyclone"
    ],
    "stats": [
      7,
      9,
      15,
      13,
      12
    ],
    "subtype": "Wind",
    "type": "Force"
  },
  "Nike": {
    "affinity": "wwwwwewww",
    "atks": [
      4,
      56,
      68
    ],
    "disinherits": [
      "death",
      "curse"
    ],
    "drops": "Dx Incense",
    "growth": "Early Growth",
    "lvl": 7,
    "mresists": "nnnnnnnndnxxns",
    "presists": "wwxwwwwx-w---x",
    "race": "Judgement",
    "skills": [
      "Kouha",
      "Dia",
      "Rakukaja",
      "-",
      "Mighty Wave",
      "Eastern Impact"
    ],
    "stats": [
      10,
      6,
      5,
      13,
      9
    ],
    "subtype": "Bless",
    "type": "Light"
  },
  "Nyarlathotep": {
    "affinity": "wwwwwwwwe",
    "atks": [
      29,
      190,
      155
    ],
    "disinherits": [
      "expel",
      "bless",
      "miracle"
    ],
    "drops": "Ebon Rope Tablet",
    "growth": "Balanced A",
    "lvl": 66,
    "mresists": "--------xwdsnS",
    "presists": "SSSSSxSSnnnn--",
    "race": "Tower",
    "skills": [
      "Slumpa",
      "Mudoon",
      "Decover",
      "Shibaboo",
      "Outoma",
      "Thunder Kick"
    ],
    "stats": [
      65,
      60,
      36,
      31,
      52
    ],
    "subtype": "Curse",
    "type": "Dark"
  },
  "Odin": {
    "affinity": "eooaoooow",
    "atks": [
      24,
      142,
      122
    ],
    "disinherits": [],
    "drops": "Harald's Bow",
    "growth": "Magic Skill",
    "lvl": 43,
    "mresists": "ssssssss-x-dsS",
    "presists": "xxxxxxxx---w--",
    "race": "Emperor",
    "skills": [
      "Petra Eyes",
      "Magnara",
      "Petrama",
      "-",
      "Dragon Whirl",
      "Magnadyne"
    ],
    "stats": [
      53,
      23,
      18,
      38,
      28
    ],
    "subtype": "Death",
    "type": "Element"
  },
  "Ogma": {
    "affinity": "aooeoooow",
    "atks": [
      9,
      79,
      99
    ],
    "disinherits": [
      "curse"
    ],
    "drops": "General Piece",
    "growth": "Tech Skill",
    "lvl": 25,
    "mresists": "VdssssssdnxWTn",
    "presists": "---------w----",
    "race": "Hierophant",
    "skills": [
      "Heat Wave",
      "-",
      "Sukunda",
      "Dekunda",
      "-",
      "Crimson Sublation"
    ],
    "stats": [
      18,
      34,
      24,
      13,
      20
    ],
    "subtype": "Ice",
    "type": "Light"
  },
  "Ogun": {
    "affinity": "wwewwwwww",
    "atks": [
      4,
      47,
      37
    ],
    "disinherits": [
      "bless",
      "miracle"
    ],
    "drops": "HP Incense",
    "growth": "Early Growth",
    "lvl": 5,
    "mresists": "wwwwss-R----TS",
    "presists": "-----------w--",
    "race": "Chariot",
    "skills": [
      "Tackle",
      "Flurry Stab",
      "Gry",
      "-",
      "Magry",
      "Mazio"
    ],
    "stats": [
      18,
      10,
      8,
      5,
      9
    ],
    "subtype": "Gravity",
    "type": "Force"
  },
  "Otohime": {
    "affinity": "eoeeoooee",
    "atks": [
      29,
      154,
      136
    ],
    "disinherits": [],
    "drops": "Double Death",
    "growth": "Vanguard Skill",
    "lvl": 50,
    "mresists": "wwwwwwwwdsxxss",
    "presists": "ssssssssssssxs",
    "race": "Strength",
    "skills": [
      "Candy Voice",
      "Traesto",
      "Nervundi",
      "Water Wall",
      "Tarukaja",
      "Gentle Wave"
    ],
    "stats": [
      48,
      63,
      32,
      25,
      33
    ],
    "subtype": "Ice",
    "type": "Light"
  },
  "Pallas Athena": {
    "affinity": "ooaoeooow",
    "atks": [
      71,
      255,
      205
    ],
    "disinherits": [
      "bless",
      "miracle"
    ],
    "drops": "Caesar Armor",
    "growth": "Balanced A",
    "lvl": 90,
    "mresists": "XXXXxxxx-x-x--",
    "presists": "RRRRRRRRRRRRRR",
    "race": "Justice",
    "skills": [
      "Deathbound",
      "-",
      "Steel Wall",
      "Ziodyne",
      "Tarukaja",
      "Mazandyne"
    ],
    "stats": [
      41,
      46,
      83,
      78,
      59
    ],
    "subtype": "Electric",
    "type": "Force"
  },
  "Phaleg": {
    "affinity": "oooooeaow",
    "atks": [
      7,
      84,
      84
    ],
    "disinherits": [
      "ice",
      "death",
      "curse"
    ],
    "drops": "Zandyne Stone",
    "growth": "Magic Skill",
    "lvl": 18,
    "mresists": "nnnnnnnndnxxns",
    "presists": "wwxwwwwx-w---x",
    "race": "Judgement",
    "skills": [
      "Twin Slash",
      "Tarunda",
      "-",
      "Mediarama",
      "Tetraja",
      "Crimson Sublation"
    ],
    "stats": [
      16,
      11,
      7,
      22,
      17
    ],
    "subtype": "Fire",
    "type": "Light"
  },
  "Pixie": {
    "affinity": "oeoooeeew",
    "atks": [
      2,
      42,
      63
    ],
    "disinherits": [
      "earth"
    ],
    "drops": "Lu Incense",
    "growth": "Pixie",
    "lvl": 5,
    "mresists": "ssR-wwww----TS",
    "presists": "-----------w--",
    "race": "Lovers",
    "skills": [
      "Dia",
      "Garu",
      "Happy Dance",
      "Zio",
      "Twinkle Punch",
      "Zionga"
    ],
    "stats": [
      5,
      10,
      7,
      16,
      18
    ],
    "subtype": "Wind",
    "type": "Element"
  },
  "Pyro Jack": {
    "affinity": "oeoooeeew",
    "atks": [
      13,
      83,
      103
    ],
    "disinherits": [
      "ice"
    ],
    "drops": "Iron Pumpkin",
    "growth": "Late Growth A",
    "lvl": 20,
    "mresists": "R-sswwww----TS",
    "presists": "-----------w--",
    "race": "Lovers",
    "skills": [
      "Agi",
      "Sweet Trap",
      "Maragi",
      "Hula of Misfortune",
      "Agilao",
      "Fire Breath"
    ],
    "stats": [
      13,
      15,
      17,
      22,
      34
    ],
    "subtype": "Fire",
    "type": "Element"
  },
  "Quetzalcoatl": {
    "affinity": "eoeeeoooe",
    "atks": [
      7,
      72,
      80
    ],
    "disinherits": [],
    "drops": "Magnadyne Stone",
    "growth": "Defense Skill",
    "lvl": 17,
    "mresists": "wwwwwwwwdsxxss",
    "presists": "ssssssssssssxs",
    "race": "World",
    "skills": [
      "Stun Bite",
      "Frei",
      "Traesto",
      "Crimson Sublation",
      "-",
      "Mazanma"
    ],
    "stats": [
      16,
      27,
      11,
      10,
      14
    ],
    "subtype": "Nuclear",
    "type": "Force"
  },
  "Satan": {
    "affinity": "oooooeaoo",
    "atks": [
      58,
      227,
      217
    ],
    "disinherits": [],
    "drops": "Megido Fire",
    "growth": "Balanced B",
    "lvl": 79,
    "mresists": "RRRRRRRRRRxxRs",
    "presists": "--x----x-w---x",
    "race": "Judgement",
    "skills": [
      "Bright Judgement",
      "-",
      "Dark Verdict",
      "-",
      "Megidolaon",
      "Samarecarm"
    ],
    "stats": [
      36,
      37,
      32,
      76,
      52
    ],
    "subtype": "Occult",
    "type": "Light"
  },
  "Sati": {
    "affinity": "oeoooooaw",
    "atks": [
      6,
      84,
      89
    ],
    "disinherits": [
      "ice",
      "death",
      "curse"
    ],
    "drops": "Full Moon Tablet",
    "growth": "Vanguard Skill",
    "lvl": 18,
    "mresists": "dVssssssdnxWTS",
    "presists": "--------w-----",
    "race": "Priestess",
    "skills": [
      "Fire Wall",
      "Dia",
      "-",
      "Diarama",
      "Recarm",
      "Azure Cessation"
    ],
    "stats": [
      16,
      17,
      17,
      8,
      11
    ],
    "subtype": "Fire",
    "type": "Light"
  },
  "Seimen Kongou": {
    "affinity": "ewwwwwwww",
    "atks": [
      4,
      65,
      46
    ],
    "disinherits": [],
    "drops": "St Incense",
    "growth": "Early Growth",
    "lvl": 5,
    "mresists": "ssR-wwww----TS",
    "presists": "-----------w--",
    "race": "Emperor",
    "skills": [
      "Garu",
      "Delyte",
      "Makajam",
      "Pulinpa",
      "Magaru",
      "Spin Kick"
    ],
    "stats": [
      12,
      8,
      5,
      11,
      9
    ],
    "subtype": "Prayer",
    "type": "Element"
  },
  "Seioubo": {
    "affinity": "oaoooooew",
    "atks": [
      21,
      139,
      134
    ],
    "disinherits": [],
    "drops": "Caesar Helm",
    "growth": "Defense Skill",
    "lvl": 44,
    "mresists": "wwwwssR-----TS",
    "presists": "-----------w--",
    "race": "Empress",
    "skills": [
      "Zanma",
      "Alsanga",
      "Freila",
      "-",
      "Darkness Nail",
      "Western Blow"
    ],
    "stats": [
      34,
      33,
      29,
      18,
      39
    ],
    "subtype": "Blast",
    "type": "Force"
  },
  "Seiryuu": {
    "affinity": "eeeeeeeee",
    "atks": [
      23,
      149,
      147
    ],
    "disinherits": [],
    "drops": "Seiryuu Gauntlet",
    "growth": "Seiryuu",
    "lvl": 49,
    "mresists": "wwwwwwwwdsxxss",
    "presists": "ssssssssssssxs",
    "race": "World",
    "skills": [
      "Ice Breath",
      "Zanma",
      "Stun Claw",
      "Ziodyne",
      "Earthly Vortex",
      "Mabufudyne"
    ],
    "stats": [
      33,
      63,
      28,
      24,
      30
    ],
    "subtype": "Ice",
    "type": "Force"
  },
  "Seiten Taisei": {
    "affinity": "ooeoaooow",
    "atks": [
      20,
      152,
      117
    ],
    "disinherits": [
      "bless",
      "miracle"
    ],
    "drops": "Koppa-Mijinhou",
    "growth": "Balanced C",
    "lvl": 48,
    "mresists": "WWxdssss----TS",
    "presists": "-----------w--",
    "race": "Chariot",
    "skills": [
      "Heavenly Hit",
      "-",
      "Magry",
      "Megidola",
      "-",
      "Genocide Fan"
    ],
    "stats": [
      53,
      35,
      48,
      23,
      28
    ],
    "subtype": "Earth",
    "type": "Force"
  },
  "Shiva": {
    "affinity": "ooeoaooow",
    "atks": [
      62,
      274,
      274
    ],
    "disinherits": [
      "bless",
      "miracle"
    ],
    "drops": "Scorching Tablet",
    "growth": "Late Growth A",
    "lvl": 96,
    "mresists": "WWdxssss----TS",
    "presists": "-----------w--",
    "race": "Chariot",
    "skills": [
      "Megaton Raid",
      "Zanma",
      "Triple Slice",
      "Garudyne",
      "-",
      "Megidolaon"
    ],
    "stats": [
      89,
      59,
      84,
      43,
      48
    ],
    "subtype": "Wind",
    "type": "Force"
  },
  "Shokuin": {
    "affinity": "eoeeeoooe",
    "atks": [
      63,
      265,
      248
    ],
    "disinherits": [],
    "drops": "Gale Tablet",
    "growth": "Defense Skill",
    "lvl": 97,
    "mresists": "wwwwwwwwdsxxss",
    "presists": "ssssssssssssxs",
    "race": "World",
    "skills": [
      "Fog Breath",
      "Fire Breath",
      "Ice Breath",
      "Gokuraku Fall",
      "Poison Breath",
      "Megidolaon"
    ],
    "stats": [
      63,
      99,
      51,
      44,
      54
    ],
    "subtype": "Gravity",
    "type": "Force"
  },
  "Shouki": {
    "affinity": "aooeoooow",
    "atks": [
      7,
      57,
      82
    ],
    "disinherits": [
      "curse"
    ],
    "drops": "Megaton Glove",
    "growth": "Defense Skill",
    "lvl": 17,
    "mresists": "TTTTTTTTdRxxTS",
    "presists": "--------------",
    "race": "Hierophant",
    "skills": [
      "Tarunda",
      "Estoma",
      "Destruction Smash",
      "-",
      "Paral Eyes",
      "Rakunda"
    ],
    "stats": [
      15,
      20,
      17,
      10,
      16
    ],
    "subtype": "Expel",
    "type": "Light"
  },
  "Skuld": {
    "affinity": "oeoooooaw",
    "atks": [
      45,
      256,
      236
    ],
    "disinherits": [
      "curse"
    ],
    "drops": "Full Moon Tablet",
    "growth": "Balanced C",
    "lvl": 88,
    "mresists": "xxxxxxxxdwxX--",
    "presists": "RRRRRRRRRRRRRR",
    "race": "Priestess",
    "skills": [
      "Mediarahan",
      "Eternal Black",
      "Samarecarm",
      "Diarahan",
      "-",
      "Hieroglyphein"
    ],
    "stats": [
      44,
      57,
      73,
      34,
      39
    ],
    "subtype": "Miracle",
    "type": "Light"
  },
  "Succubus": {
    "affinity": "eweeewwwe",
    "atks": [
      37,
      177,
      170
    ],
    "disinherits": [
      "expel",
      "bless",
      "miracle"
    ],
    "drops": "Silver Medusa",
    "growth": "Late Growth B",
    "lvl": 53,
    "mresists": "ddddddddxxddrs",
    "presists": "xxxxxxxx----xx",
    "race": "Moon",
    "skills": [
      "Luna Trap",
      "Dormina",
      "Marin Karin",
      "Mudoon",
      "Makarakarn",
      "Moon Shatterer"
    ],
    "stats": [
      26,
      31,
      34,
      33,
      39
    ],
    "subtype": "Nerve",
    "type": "Dark"
  },
  "Susanoo": {
    "affinity": "wwewwwwww",
    "atks": [
      20,
      197,
      157
    ],
    "disinherits": [
      "bless",
      "miracle"
    ],
    "drops": "Kusanagi-no-Tsurugi",
    "growth": "Late Growth B",
    "lvl": 59,
    "mresists": "wwwwssR-----TS",
    "presists": "-----------w--",
    "race": "Chariot",
    "skills": [
      "Bonecrusher",
      "-",
      "Eternal Black",
      "Earthly Vortex",
      "Deadly Fist",
      "Zandyne"
    ],
    "stats": [
      66,
      45,
      61,
      32,
      37
    ],
    "subtype": "Blast",
    "type": "Force"
  },
  "Suzaku": {
    "affinity": "eeeeeeeee",
    "atks": [
      34,
      162,
      147
    ],
    "disinherits": [
      "ice"
    ],
    "drops": "Suzaku Helmet",
    "growth": "Suzaku",
    "lvl": 55,
    "mresists": "ssn-wwTx-s-sTs",
    "presists": "nn-nn-xnXXXX--",
    "race": "Sun",
    "skills": [
      "Agilao",
      "Wing Flap",
      "Fire Breath",
      "-",
      "Liftoma",
      "Maragidyne"
    ],
    "stats": [
      37,
      27,
      36,
      68,
      53
    ],
    "subtype": "Fire",
    "type": "Element"
  },
  "Take-Mikazuchi": {
    "affinity": "aooeoooow",
    "atks": [
      17,
      108,
      128
    ],
    "disinherits": [
      "curse"
    ],
    "drops": "Futsu-no-Mitama",
    "growth": "Melee Skill",
    "lvl": 39,
    "mresists": "ssDsdVssdnxWTn",
    "presists": "---------w----",
    "race": "Hierophant",
    "skills": [
      "Sanraigeki",
      "Dekaja",
      "-",
      "Hamaon",
      "-",
      "Wolf Fang"
    ],
    "stats": [
      26,
      45,
      35,
      21,
      28
    ],
    "subtype": "Electric",
    "type": "Light"
  },
  "Tenjiku Tokubei": {
    "affinity": "eeeeeeeee",
    "atks": [
      7,
      125,
      95
    ],
    "disinherits": [],
    "drops": "Jingle Whip",
    "growth": "Balanced C",
    "lvl": 30,
    "mresists": "SSSSSSSSSSSSSS",
    "presists": "SSSSSSSSSSSSSS",
    "race": "Fool",
    "skills": [
      "Sweet Trap",
      "Quikka",
      "Mamagnara",
      "Makakaja",
      "Samarecarm",
      "Fire Breath"
    ],
    "stats": [
      25,
      34,
      29,
      31,
      32
    ],
    "subtype": "Normal",
    "type": "Force"
  },
  "Tensen Nyannyan": {
    "affinity": "oeoooooaw",
    "atks": [
      18,
      153,
      148
    ],
    "disinherits": [
      "death",
      "curse"
    ],
    "drops": "Kokonoe Raijinhou",
    "growth": "Tech Skill",
    "lvl": 46,
    "mresists": "ssssTTTTddxxRS",
    "presists": "---x--xx-----w",
    "race": "Priestess",
    "skills": [
      "Needle Rush",
      "Mediarama",
      "Paraladi",
      "-",
      "Heat Wave",
      "Samarecarm"
    ],
    "stats": [
      28,
      33,
      41,
      18,
      23
    ],
    "subtype": "Expel",
    "type": "Light"
  },
  "Thor": {
    "affinity": "aooeoooow",
    "atks": [
      36,
      131,
      156
    ],
    "disinherits": [
      "curse"
    ],
    "drops": "Megin Gjord",
    "growth": "Balanced A",
    "lvl": 52,
    "mresists": "ssDsdVssdnxWTn",
    "presists": "---------w----",
    "race": "Hierophant",
    "skills": [
      "Mazionga",
      "-",
      "Tetraja",
      "Ziodyne",
      "-",
      "Earth Slicer"
    ],
    "stats": [
      30,
      55,
      45,
      25,
      33
    ],
    "subtype": "Electric",
    "type": "Light"
  },
  "Triglav": {
    "affinity": "ooaoeooow",
    "atks": [
      12,
      81,
      56
    ],
    "disinherits": [
      "bless",
      "miracle"
    ],
    "drops": "Poisma Stone",
    "growth": "Melee Skill",
    "lvl": 19,
    "mresists": "wwwwssR-----TS",
    "presists": "-----------w--",
    "race": "Justice",
    "skills": [
      "Double Thrust",
      "Zio",
      "Mazio",
      "-",
      "Gokuraku Fall",
      "Mazan"
    ],
    "stats": [
      12,
      17,
      25,
      21,
      17
    ],
    "subtype": "Electric",
    "type": "Force"
  },
  "Tyr": {
    "affinity": "wwwwewwww",
    "atks": [
      20,
      165,
      132
    ],
    "disinherits": [
      "bless",
      "miracle"
    ],
    "drops": "Gleipnir",
    "growth": "Melee Skill",
    "lvl": 54,
    "mresists": "wwwwssR-----TS",
    "presists": "-----------w--",
    "race": "Justice",
    "skills": [
      "Lightning Kick",
      "Western Blow",
      "-",
      "Zandyne",
      "Magry",
      "Binal Strike"
    ],
    "stats": [
      27,
      32,
      57,
      52,
      35
    ],
    "subtype": "Blast",
    "type": "Force"
  },
  "Urd": {
    "affinity": "oeoooooaw",
    "atks": [
      15,
      129,
      129
    ],
    "disinherits": [
      "curse"
    ],
    "drops": "Avenir",
    "growth": "Rear Guard Skill",
    "lvl": 37,
    "mresists": "ssssTTTTddxxRS",
    "presists": "---x--xx-----w",
    "race": "Priestess",
    "skills": [
      "Pen Patra",
      "Diarama",
      "Estoma",
      "Petradi",
      "-",
      "Eternal Black"
    ],
    "stats": [
      25,
      27,
      34,
      15,
      20
    ],
    "subtype": "Prayer",
    "type": "Light"
  },
  "Urvashi": {
    "affinity": "oooooaeow",
    "atks": [
      12,
      75,
      51
    ],
    "disinherits": [
      "fire"
    ],
    "drops": "Nervundi Stone",
    "growth": "Magic Skill",
    "lvl": 14,
    "mresists": "-Rsswwww----TS",
    "presists": "-----------w--",
    "race": "Magician",
    "skills": [
      "Bufula",
      "Mabufu",
      "-",
      "Sexy Dance",
      "Mabufula",
      "Needle Rush"
    ],
    "stats": [
      13,
      9,
      15,
      21,
      9
    ],
    "subtype": "Ice",
    "type": "Element"
  },
  "Usas": {
    "affinity": "oeoooooaw",
    "atks": [
      22,
      168,
      163
    ],
    "disinherits": [
      "ice",
      "death",
      "curse"
    ],
    "drops": "Peacemaker",
    "growth": "Magic Skill",
    "lvl": 53,
    "mresists": "dVssssssdnxWTS",
    "presists": "--------w-----",
    "race": "Priestess",
    "skills": [
      "Posumudi",
      "Patra",
      "Myriad Arrows",
      "Diarahan",
      "-",
      "Crimson Sublation"
    ],
    "stats": [
      31,
      34,
      46,
      21,
      26
    ],
    "subtype": "Fire",
    "type": "Light"
  },
  "Varuna": {
    "affinity": "oooooaeow",
    "atks": [
      32,
      165,
      125
    ],
    "disinherits": [
      "fire"
    ],
    "drops": "Gokufu Tennoh",
    "growth": "Magic Skill",
    "lvl": 47,
    "mresists": "-Rsswwww----TS",
    "presists": "-----------w--",
    "race": "Magician",
    "skills": [
      "Bufula",
      "Mabufula",
      "Mabufudyne",
      "-",
      "Water Wall",
      "Mighty Wave"
    ],
    "stats": [
      33,
      23,
      42,
      47,
      18
    ],
    "subtype": "Ice",
    "type": "Element"
  },
  "Verdandi": {
    "affinity": "wewwwwwww",
    "atks": [
      20,
      190,
      180
    ],
    "disinherits": [
      "curse"
    ],
    "drops": "Holy Comet",
    "growth": "Late Growth B",
    "lvl": 61,
    "mresists": "ssssTTTTddxxRS",
    "presists": "---x--xx-----w",
    "race": "Priestess",
    "skills": [
      "Media",
      "Recarm",
      "Diarama",
      "Azure Cessation",
      "Eternal White",
      "Mediarahan"
    ],
    "stats": [
      35,
      41,
      52,
      25,
      30
    ],
    "subtype": "Prayer",
    "type": "Light"
  },
  "Verethragna": {
    "affinity": "ooaoeooow",
    "atks": [
      18,
      124,
      94
    ],
    "disinherits": [
      "bless",
      "miracle"
    ],
    "drops": "Egili's Helmet",
    "growth": "Tech Skill",
    "lvl": 37,
    "mresists": "wwwwss-R----TS",
    "presists": "-----------w--",
    "race": "Justice",
    "skills": [
      "Gryva",
      "Thunder Kick",
      "Mazio",
      "-",
      "Magry",
      "Eternal White"
    ],
    "stats": [
      20,
      25,
      44,
      39,
      27
    ],
    "subtype": "Gravity",
    "type": "Force"
  },
  "Vesta": {
    "affinity": "wwwwwwwew",
    "atks": [
      4,
      54,
      54
    ],
    "disinherits": [
      "ice"
    ],
    "drops": "Soma",
    "growth": "Early Growth",
    "lvl": 6,
    "mresists": "dxWWssss----TS",
    "presists": "-----------w--",
    "race": "Empress",
    "skills": [
      "Frei",
      "Dia",
      "Zio",
      "-",
      "Crimson Sublation",
      "Freila"
    ],
    "stats": [
      11,
      11,
      10,
      7,
      8
    ],
    "subtype": "Fire",
    "type": "Force"
  },
  "Vidofnir": {
    "affinity": "oeoooeeeo",
    "atks": [
      13,
      113,
      103
    ],
    "disinherits": [],
    "drops": "Papageno",
    "growth": "Late Growth A",
    "lvl": 24,
    "mresists": "ssn-wwTx-s-sTs",
    "presists": "nn-nn-xnXXXX--",
    "race": "Sun",
    "skills": [
      "Bufu",
      "Mabufu",
      "-",
      "Spike Claw",
      "Magarula",
      "Bright Judgement"
    ],
    "stats": [
      21,
      13,
      19,
      43,
      28
    ],
    "subtype": "Bless",
    "type": "Element"
  },
  "Vishnu": {
    "affinity": "eooaoooow",
    "atks": [
      53,
      247,
      212
    ],
    "disinherits": [],
    "drops": "Light Wave Tablet",
    "growth": "Balanced A",
    "lvl": 86,
    "mresists": "ssn-wwTx-s-sTs",
    "presists": "nn-nn-xnXXXX--",
    "race": "Emperor",
    "skills": [
      "Garula",
      "Garudyne",
      "Marin Karin",
      "Magnadyne",
      "Bufudyne",
      "Earth Slicer"
    ],
    "stats": [
      86,
      39,
      34,
      71,
      44
    ],
    "subtype": "Miracle",
    "type": "Element"
  },
  "Vohu Manah": {
    "affinity": "oooooeaow",
    "atks": [
      73,
      269,
      249
    ],
    "disinherits": [
      "death",
      "curse"
    ],
    "drops": "Venity Tablet",
    "growth": "Balanced C",
    "lvl": 94,
    "mresists": "RRRRRRRRRRxxRs",
    "presists": "--x----x-w---x",
    "race": "Judgement",
    "skills": [
      "Makouha",
      "Binal Strike",
      "-",
      "Mahama",
      "Hieroglyphein",
      "Mediarahan"
    ],
    "stats": [
      48,
      43,
      38,
      87,
      61
    ],
    "subtype": "Expel",
    "type": "Light"
  },
  "Yama": {
    "affinity": "aooeoooow",
    "atks": [
      3,
      55,
      55
    ],
    "disinherits": [
      "curse"
    ],
    "drops": "Para Stone",
    "growth": "Late Growth B",
    "lvl": 4,
    "mresists": "TTTTTTTTdRxxTS",
    "presists": "--------------",
    "race": "Hierophant",
    "skills": [
      "Ichimonji Slash",
      "Rakukaja",
      "-",
      "Alsanga",
      "Hamaon",
      "Tarukaja"
    ],
    "stats": [
      15,
      17,
      12,
      15,
      7
    ],
    "subtype": "Expel",
    "type": "Light"
  },
  "Yamaoka": {
    "affinity": "wwwewwwww",
    "atks": [
      30,
      202,
      172
    ],
    "disinherits": [
      "death",
      "curse"
    ],
    "drops": "Quarter Moon Tablet",
    "growth": "Late Growth B",
    "lvl": 60,
    "mresists": "RRRRRRRRRRxxRs",
    "presists": "--x----x-w---x",
    "race": "Judgement",
    "skills": [
      "Lullaby",
      "Love Whip",
      "Diarahan",
      "Makarakarn",
      "Makouha",
      "Deadly Fist"
    ],
    "stats": [
      50,
      29,
      24,
      61,
      75
    ],
    "subtype": "Miracle",
    "type": "Light"
  },
  "Yatagarasu": {
    "affinity": "oeoooeeeo",
    "atks": [
      22,
      135,
      120
    ],
    "disinherits": [],
    "drops": "Ameno-Murakumo",
    "growth": "Tech Skill",
    "lvl": 41,
    "mresists": "ssn-wwTx-s-sTs",
    "presists": "nn-nn-xnXXXX--",
    "race": "Sun",
    "skills": [
      "Beak",
      "Magnara",
      "Mamagnara",
      "-",
      "Dive",
      "Mamagnadyne"
    ],
    "stats": [
      30,
      22,
      29,
      56,
      41
    ],
    "subtype": "Miracle",
    "type": "Element"
  }
}