{
  "Agares": {
    "command": {"Gigajama": 58, "Mazandyne": 3317, "Tetrakarn": 59},
    "lvl": 57,
    "passive": {"Fire Amp": 3321, "Force Amp": 3319, "Phys Drain": 0},
    "race": "Fallen",
    "resists": "ss--sw",
    "stats": [458, 177, 21, 17, 17, 18]
  },
  "Amaterasu": {
    "command": {"Prayer": 0, "Recarmloss": 74},
    "lvl": 73,
    "race": "Megami",
    "resists": "-n--n-",
    "stats": [465, 306, 21, 29, 20, 19],
    "unique": true
  },
  "Ananta": {
    "command": {"Makarakarn": 0},
    "lvl": 71,
    "passive": {"Attack All": 72},
    "race": "Snake",
    "resists": "-sss-w",
    "stats": [665, 180, 30, 19, 24, 13],
    "unique": true
  },
  "Arioch": {
    "command": {"Deathbound": 0, "Tetrakarn": 0},
    "lvl": 56,
    "race": "Vile",
    "resists": "nws-sw",
    "stats": [555, 70, 23, 14, 18, 17],
    "unique": true
  },
  "Astaroth": {
    "command": {"Deathbound": 54},
    "lvl": 51,
    "passive": {"Null Curse": 0},
    "race": "Tyrant",
    "resists": "-wsss-",
    "stats": [372, 136, 27, 17, 11, 13],
    "unique": true
  },
  "Asura": {
    "command": {"Megidolaon": 0},
    "lvl": 80,
    "race": "Deity",
    "resists": "-d-s--",
    "stats": [824, 206, 28, 23, 23, 22],
    "unique": true
  },
  "Baphomet": {
    "command": {"Holy Dance": 0},
    "lvl": 69,
    "passive": {"Avenge": 71},
    "race": "Vile",
    "resists": "-ddsss",
    "stats": [522, 176, 26, 19, 18, 22],
    "unique": true
  },
  "Barong": {
    "command": {"Maziodyne": 3319},
    "lvl": 63,
    "passive": {"Elec Amp": 3321, "Mana Aid": 0},
    "race": "Avatar",
    "resists": "-s-dw-",
    "stats": [486, 170, 23, 22, 18, 17]
  },
  "Behemoth": {
    "lvl": 70,
    "passive": {"Dual Shadow": 3319, "Extra Savings": 0},
    "race": "Wilder",
    "resists": "-wss--",
    "stats": [808, 64, 37, 10, 31, 8]
  },
  "Black Maria": {
    "command": {"Diarahan": 0, "Mabufudyne": 3319},
    "lvl": 66,
    "passive": {"Critical Heal": 3317, "Ice Drain": 67},
    "race": "Megami",
    "resists": "---ws-",
    "stats": [415, 294, 20, 26, 17, 19]
  },
  "Cabracan": {
    "command": {"Multi-Strike": 0},
    "lvl": 68,
    "passive": {"Avenge": 69, "Phys Amp": 3317},
    "race": "Beast",
    "resists": "-s--wr",
    "stats": [686, 156, 25, 10, 30, 19]
  },
  "Catoblepas": {
    "command": {"Deathbound": 0},
    "lvl": 54,
    "passive": {"+Stone": 3319, "Attack All": 55},
    "race": "Wilder",
    "resists": "-wsr-w",
    "stats": [426, 144, 22, 18, 17, 13]
  },
  "Culebre": {
    "command": {"Bufudyne": 0, "Cursed Dance": 48, "Might Call": 3318},
    "lvl": 47,
    "passive": {"Ice Repel": 49, "Life Surge": 3321},
    "race": "Dragon",
    "resists": "-wrss-",
    "stats": [360, 130, 16, 18, 13, 13]
  },
  "Fafnir": {
    "command": {"Deathbound": 3319, "Final Strike": 3317},
    "lvl": 64,
    "passive": {"Force Drain": 0},
    "race": "Dragon",
    "resists": "swnwd-",
    "stats": [552, 162, 24, 17, 21, 18]
  },
  "Ganesha": {
    "command": {"Mazandyne": 3320, "Megido": 0},
    "lvl": 68,
    "passive": {"Drain Hit": 3319, "Force Drain": 0},
    "race": "Genma",
    "resists": "--dwss",
    "stats": [564, 182, 28, 23, 26, 7]
  },
  "Garuda": {
    "command": {"Megidolaon": 0},
    "lvl": 71,
    "race": "Avian",
    "resists": "-s-swn",
    "stats": [534, 178, 22, 18, 18, 28]
  },
  "Huoniao": {
    "command": {"Makarakarn": 3317, "Maragidyne": 0, "Megido": 57},
    "lvl": 56,
    "passive": {"Anti-Elec": 3321, "Fire Amp": 3319},
    "race": "Avian",
    "resists": "-nw---",
    "stats": [420, 158, 14, 23, 14, 21]
  },
  "Ishtar": {
    "command": {"Diarahan": 30, "Recarm": 0},
    "lvl": 29,
    "race": "Megami",
    "resists": "---s-n",
    "stats": [190, 151, 9, 17, 9, 10]
  },
  "Jahi": {
    "command": {"Maziodyne": 3319, "Recarmloss": 0},
    "lvl": 67,
    "passive": {"Elec Amp": 3317},
    "race": "Femme",
    "resists": "-swss-",
    "stats": [428, 288, 21, 26, 17, 19]
  },
  "Kabuso": {
    "command": {"Agi": 0, "Zan": 4},
    "lvl": 2,
    "race": "Beast",
    "resists": "-s-w-s",
    "stats": [33, 21, 4, 6, 4, 4]
  },
  "Kazfiel": {
    "command": {"Judgement": 0},
    "lvl": 58,
    "passive": {"Ice Repel": 0},
    "race": "Divine",
    "resists": "s-r---",
    "stats": [483, 152, 23, 18, 20, 13]
  },
  "Laksmi": {
    "command": {"Mediarahan": 50, "Samarecarm": 52},
    "lvl": 48,
    "passive": {"Mana Surge": 0},
    "race": "Megami",
    "resists": "----wr",
    "stats": [279, 304, 14, 23, 14, 13]
  },
  "Loki": {
    "command": {"Megido": 65},
    "lvl": 64,
    "passive": {"Anti-All": 0},
    "race": "Tyrant",
    "resists": "ssssss",
    "stats": [522, 174, 19, 23, 23, 15],
    "unique": true
  },
  "Lorelei": {
    "command": {"Amrita": 3318, "Diarahan": 0, "Makajamaon": 35},
    "lvl": 33,
    "passive": {"Mana Surge": 3319, "Vigilant": 0},
    "race": "Fairy",
    "resists": "---ssw",
    "stats": [200, 153, 8, 18, 7, 16]
  },
  "Lucifuge": {
    "command": {"Agidyne": 35},
    "lvl": 34,
    "passive": {"Anti-Phys": 0},
    "race": "Tyrant",
    "resists": "sw-sss",
    "stats": [233, 131, 12, 13, 11, 14],
    "unique": true
  },
  "Macabre": {
    "command": {"Final Strike": 66},
    "lvl": 65,
    "passive": {"Fire Drain": 0, "Pierce": 3319},
    "race": "Jaki",
    "resists": "-d--ww",
    "stats": [510, 200, 27, 15, 20, 19]
  },
  "Mahakala": {
    "command": {"Might Call": 27},
    "lvl": 26,
    "passive": {"Ares Aid": 0},
    "race": "Deity",
    "resists": "-sws-s",
    "stats": [210, 83, 12, 12, 11, 7]
  },
  "Metatron": {
    "lvl": 89,
    "passive": {"Victory Cry": 0},
    "race": "Divine",
    "resists": "nnwwnr",
    "stats": [904, 242, 29, 32, 24, 20],
    "unique": true
  },
  "Mithras": {
    "command": {"Death Call": 63, "Tetrakarn": 64},
    "lvl": 62,
    "passive": {"+Mute": 3317, "Pierce": 3319},
    "race": "Fallen",
    "resists": "-wwrrw",
    "stats": [489, 166, 22, 21, 17, 18]
  },
  "Murmur": {
    "command": {"Death Call": 0, "Holy Strike": 74},
    "lvl": 73,
    "passive": {"Life Lift": 3321, "Phys Repel": 3319},
    "race": "Fallen",
    "resists": "-wrwrw",
    "stats": [570, 196, 25, 25, 19, 19]
  },
  "Norn": {
    "command": {"Prayer": 56},
    "lvl": 55,
    "passive": {"Mana Aid": 57},
    "race": "Megami",
    "resists": "-s--rs",
    "stats": [345, 231, 17, 22, 14, 18],
    "unique": true
  },
  "Nyarlathotep": {
    "lvl": 78,
    "passive": {"Mana Aid": 0},
    "race": "Vile",
    "resists": "-sssss",
    "stats": [485, 300, 30, 22, 19, 23],
    "unique": true
  },
  "Odin": {
    "command": {"Shield All": 40},
    "lvl": 38,
    "passive": {"Null Elec": 0},
    "race": "Deity",
    "resists": "--snws",
    "stats": [296, 142, 11, 19, 14, 10],
    "unique": true
  },
  "Okuninushi": {
    "command": {"Holy Strike": 0},
    "lvl": 87,
    "passive": {"Anti-All": 89},
    "race": "Kishin",
    "resists": "-r--sw",
    "stats": [912, 218, 31, 22, 27, 23],
    "unique": true
  },
  "Ongyo-ki": {
    "command": {"Hassohappa": 0, "Piercing Hit": 85},
    "lvl": 83,
    "passive": {"Null Elec": 0},
    "race": "Touki",
    "resists": "-w-n--",
    "stats": [749, 104, 31, 21, 24, 23],
    "unique": true
  },
  "Orochi": {
    "command": {"Deathbound": 3321, "Hassohappa": 61},
    "lvl": 59,
    "passive": {"Ares Aid": 3318, "Crisis Might": 60},
    "race": "Snake",
    "resists": "-dw--s",
    "stats": [560, 73, 26, 14, 21, 14]
  },
  "Rangda": {
    "command": {"Diajama": 51, "Maragi": 3317},
    "lvl": 49,
    "passive": {"Fire Amp": 3320, "Phys Repel": 52, "Retaliate": 3319},
    "race": "Femme",
    "resists": "r--wss",
    "stats": [330, 183, 20, 12, 17, 16]
  },
  "Remiel": {
    "command": {"Samarecarm": 0},
    "lvl": 75,
    "passive": {"Phys Drain": 0},
    "race": "Divine",
    "resists": "ns-s--",
    "stats": [639, 282, 27, 26, 19, 19],
    "unique": true
  },
  "Rukh": {
    "command": {"Mabufudyne": 47},
    "lvl": 43,
    "passive": {"Dual Shadow": 0},
    "race": "Avian",
    "resists": "-w-ss-",
    "stats": [366, 110, 19, 12, 18, 12]
  },
  "Seiryuu": {
    "command": {"Mazio": 48, "Maziodyne": 3321},
    "lvl": 46,
    "passive": {"Elec Amp": 49, "Elec Repel": 50},
    "race": "Snake",
    "resists": "-sssws",
    "stats": [360, 116, 19, 12, 14, 17]
  },
  "Shiva": {
    "command": {"Hassohappa": 0},
    "lvl": 61,
    "race": "Deity",
    "resists": "sssssn",
    "stats": [504, 162, 23, 20, 23, 18],
    "unique": true
  },
  "Spriggan": {
    "lvl": 54,
    "passive": {"Dual Shadow": 55, "Life Surge": 3319},
    "race": "Fairy",
    "resists": "s--nnw",
    "stats": [432, 156, 12, 24, 18, 16]
  },
  "Sraosha": {
    "command": {"Mazandyne": 3319, "Maziodyne": 0, "Prayer": 66},
    "lvl": 65,
    "passive": {"Elec Amp": 3317, "Elec Drain": 0},
    "race": "Divine",
    "resists": "--wd--",
    "stats": [520, 204, 15, 28, 15, 23]
  },
  "Susano-o": {
    "command": {"Mazandyne": 0, "Piercing Hit": 0},
    "lvl": 72,
    "race": "Deity",
    "resists": "r-wsd-",
    "stats": [552, 194, 29, 25, 20, 12],
    "unique": true
  },
  "Tao Tie": {
    "command": {"Makajamaon": 0, "Megido": 48},
    "lvl": 47,
    "race": "Vile",
    "resists": "--ss-w",
    "stats": [352, 195, 15, 18, 17, 12],
    "unique": true
  },
  "Tokebi": {
    "command": {"Mow Down": 27},
    "lvl": 26,
    "passive": {"Anti-Fire": 0},
    "race": "Touki",
    "resists": "-sss-w",
    "stats": [162, 92, 11, 11, 10, 10]
  },
  "Troll": {
    "command": {"Mabufudyne": 3317, "Piercing Hit": 0},
    "lvl": 69,
    "passive": {"Ice Amp": 3319},
    "race": "Fairy",
    "resists": "-wdw--",
    "stats": [528, 202, 30, 23, 19, 13]
  },
  "Tschaggatta": {
    "command": {"Judgement": 62, "Tetrakarn": 3319},
    "lvl": 60,
    "passive": {"Fire Amp": 3317},
    "race": "Genma",
    "resists": "--dwrs",
    "stats": [504, 135, 12, 20, 20, 24]
  },
  "Vivian": {
    "command": {"Diarahan": 3319, "Drain": 0, "Ziodyne": 46},
    "lvl": 45,
    "passive": {"+Paralyze": 3318, "Elec Repel": 47, "Mana Surge": 0},
    "race": "Fairy",
    "resists": "-s-ds-",
    "stats": [261, 261, 10, 22, 13, 13]
  },
  "Yaksa": {
    "command": {"Deathbound": 53, "Diarahan": 0},
    "lvl": 52,
    "passive": {"Null Fire": 54, "Pierce": 3321},
    "race": "Touki",
    "resists": "-n-sws",
    "stats": [462, 63, 25, 11, 14, 18]
  },
  "Yurlungur": {
    "command": {"Dream Feast": 0, "Holy Dance": 86},
    "lvl": 85,
    "passive": {"Anti-Most": 0},
    "race": "Snake",
    "resists": "-sd--s",
    "stats": [791, 224, 35, 22, 28, 16],
    "unique": true
  },
  "Zouchou": {
    "command": {"Agidyne": 51},
    "lvl": 50,
    "race": "Kishin",
    "resists": "----wn",
    "stats": [536, 130, 21, 15, 17, 12],
    "unique": true
  }
}
