{
  "baseAtks": [
    "Move",
    "Range"
  ],
  "baseStats": [
    "HP",
    "MP",
    "St",
    "In",
    "Ma",
    "Vi",
    "Ag",
    "Lu"
  ],
  "raceRes": {
    "Amatsu": "--wss-s-sn",
    "Avatar": "sw---sw-s1",
    "Avian": "sw-sw-s-s2",
    "Beast": "sw---sw-s1",
    "Brute": "-sw------2",
    "Deity": "-sswsss-sn",
    "Divine": "-sssw-s-s2",
    "Dragon": "ws-ww---sn",
    "Drake": "ws-ww----n",
    "Element": "sssssswssn",
    "Fairy": "ssssssw-s2",
    "Fallen": "-sssws---1",
    "Femme": "-wwss-s-sn",
    "Flight": "sws-w-s-s2",
    "Foul": "-s-------s",
    "Genma": "-sssssw-s1",
    "Herald": "--ss--s-sn",
    "Holy": "sw---sw-s1",
    "Human": "-s------s2",
    "Jaki": "-sw------2",
    "Jirae": "-sw--sw-s2",
    "Kishin": "-swss-s-sn",
    "Kunitsu": "--wss-s-sn",
    "Machine": "----www--n",
    "Megami": "-ssww-s-sn",
    "Night": "ssssssw-sn",
    "Raptor": "swssw-s--2",
    "Snake": "ws-w-w--sn",
    "Soshin": "--sws-s-sn",
    "Spirit": "-ssssss-fn",
    "Tenma": "-swss-s-sn",
    "Touki": "-sw------2",
    "Tyrant": "--ssssss-n",
    "Vile": "-wsws-s-sn",
    "Wilder": "sw---sw-s1",
    "Yoma": "ssssssw-sn"
  },
  "resistCodes": {
    "-": 100,
    "1": 10,
    "2": 20,
    "f": 1999,
    "n": 0,
    "s": 50,
    "w": 1200
  },
  "resistElems": [
    "ground",
    "air",
    "fire",
    "ice",
    "elec",
    "force",
    "giga",
    "almighty",
    "light",
    "dark"
  ],
  "skillElems": [
    "phys",
    "ailment",
    "recovery",
    "support"
  ],
  "species": [
    ["DEITIES", "Deity|ll",   "Megami|ln",  "Vile|dl"],
    ["ICONS",   "Tenma|lc",   "Kishin|ln",  "Amatsu|ll",  "Kunitsu|lc", "Femme|lc"],
    ["NETHERS", "Tyrant|dc",  "Night|dl",   "Yoma|dn"],
    ["AERIALS", "Divine|ll",  "Fallen|dc"],
    ["DRAGONS", "Dragon|lc",  "Snake|nn",   "Drake|dl"],
    ["FAIRIES", "Genma|ln",   "Jirae|nn",   "Fairy|nn"],
    ["AVIANS",  "Avian|nl",   "Flight|nc",  "Raptor|dn"],
    ["BEASTS",  "Avatar|ll",  "Holy|nn",    "Beast|nn",   "Wilder|dn"],
    ["BRUTES",  "Brute|nl",   "Touki|nc",   "Jaki|dl"],
    ["SPIRITS", "Spirit|dc",  "Foul|dc"],
    ["GODLIES", "Soshin|lc",  "Herald|ll"],
    ["METAS",   "Element|ln", "Machine|nn", "Human|nn"]
  ]
}
