[
  {
    "category": "Story Progression",
    "unlocked": true,
    "conditions": {
      "Sukuna-Hikona": "Defeat in Kanda-no-Yashiro",
      "Medusa": "Defeat in Sky Tree",
      "Zhong Kui": "Defeat in Tsukiji Hongwanji",
      "Quetzalcoatl": "Defeat in Kinshicho",
      "Tenkai": "Recruit from Hills Building",
      "Bishamonten": "Defeat in Tokugawa Mandala",
      "Jikokuten": "Defeat in Tokugawa Mandala",
      "Koumokuten": "Defeat in Tokugawa Mandala",
      "Zouchouten": "Defeat in Tokugawa Mandala",
      "Marishiten": "Defeat in Tokugawa Mandala",
      "Adramelech": "Defeat in Tsukiji Hongwanji",
      "Azrael": "Defeat in Eastern Kingdom of Mikado",
      "Belial": "Defeat in Lucifer Palace",
      "Lucifuge": "Defeat in Lucifer Palace",
      "Samyaza": "Defeat in Lucifer Palace",
      "Odin": "Defeat in Cosmic Egg",
      "Baal,Beelzebub" :"Defeat in Cosmic Egg",
      "Apsu": "Defeat in Cosmic Egg",
      "Seth": "Defeat in Cosmic Egg",
      "Inanna": "Defeat in Cosmic Egg",
      "Maitreya,Mitra-Buddha": "Defeat in Cosmic Egg",
      "Krishna": "Defeat in Cosmic Egg, Recruit from Kanda-no-Yashiro",
      "Metatron,Lucifer,Merkabah,Satan": "Clear Bonds or Anarchy ending",
      "Chironnupu": "New Game+"
    }
  },
  {
    "category": "Challenge Quests",
    "unlocked": true,
    "conditions": {
      "Take-Mikazuchi": "Clear \"u have a guest!!!\"",
      "Izanami": "Clear \"Where the Corpse Went\""
    }
  },
  {
    "category": "Twisted Tokyo",
    "unlocked": true,
    "conditions": {
      "Mother Harlot": "Defeat in Twisted Tokyo",
      "Trumpeter": "Defeat in Twisted Tokyo",
      "Pale Rider": "Defeat in Twisted Tokyo",
      "Black Rider": "Defeat in Twisted Tokyo",
      "Red Rider": "Defeat in Twisted Tokyo",
      "White Rider": "Defeat in Twisted Tokyo",
      "Matador": "Defeat in Twisted Tokyo",
      "David": "Defeat in Twisted Tokyo"
    }
  },
  {
    "category": "Downloadable Content",
    "unlocked": false,
    "conditions": {
      "Cleopatra": "The Inverted Pyramid",
      "Mephisto": "A Trip to Hawaii"
    }
  }
]
